meld_cli/__init__.py
meld_cli/api.py
meld_cli/config.py
meld_cli/entities.py
meld_cli/ide.py
meld_cli/indexer.py
meld_cli/main.py
meld_cli/scrubber.py
meld_cli/sync.py
meld_cli/version.py
meld_memory-0.1.9.dist-info/METADATA
meld_memory-0.1.9.dist-info/WHEEL
meld_memory-0.1.9.dist-info/entry_points.txt
meld_memory-0.1.9.dist-info/RECORD
